clearml_agent/__init__.py
clearml_agent/__main__.py
clearml_agent/complete.py
clearml_agent/config.py
clearml_agent/definitions.py
clearml_agent/errors.py
clearml_agent/session.py
clearml_agent/version.py
clearml_agent/_vendor/__init__.py
clearml_agent/_vendor/six.py
clearml_agent/_vendor/typing_extensions.py
clearml_agent/_vendor/attr/__init__.py
clearml_agent/_vendor/attr/_cmp.py
clearml_agent/_vendor/attr/_compat.py
clearml_agent/_vendor/attr/_config.py
clearml_agent/_vendor/attr/_funcs.py
clearml_agent/_vendor/attr/_make.py
clearml_agent/_vendor/attr/_next_gen.py
clearml_agent/_vendor/attr/_version_info.py
clearml_agent/_vendor/attr/converters.py
clearml_agent/_vendor/attr/exceptions.py
clearml_agent/_vendor/attr/filters.py
clearml_agent/_vendor/attr/setters.py
clearml_agent/_vendor/attr/validators.py
clearml_agent/_vendor/attrs/__init__.py
clearml_agent/_vendor/attrs/converters.py
clearml_agent/_vendor/attrs/exceptions.py
clearml_agent/_vendor/attrs/filters.py
clearml_agent/_vendor/attrs/setters.py
clearml_agent/_vendor/attrs/validators.py
clearml_agent/_vendor/chardet/__init__.py
clearml_agent/_vendor/chardet/big5freq.py
clearml_agent/_vendor/chardet/big5prober.py
clearml_agent/_vendor/chardet/chardistribution.py
clearml_agent/_vendor/chardet/charsetgroupprober.py
clearml_agent/_vendor/chardet/charsetprober.py
clearml_agent/_vendor/chardet/codingstatemachine.py
clearml_agent/_vendor/chardet/cp949prober.py
clearml_agent/_vendor/chardet/enums.py
clearml_agent/_vendor/chardet/escprober.py
clearml_agent/_vendor/chardet/escsm.py
clearml_agent/_vendor/chardet/eucjpprober.py
clearml_agent/_vendor/chardet/euckrfreq.py
clearml_agent/_vendor/chardet/euckrprober.py
clearml_agent/_vendor/chardet/euctwfreq.py
clearml_agent/_vendor/chardet/euctwprober.py
clearml_agent/_vendor/chardet/gb2312freq.py
clearml_agent/_vendor/chardet/gb2312prober.py
clearml_agent/_vendor/chardet/hebrewprober.py
clearml_agent/_vendor/chardet/jisfreq.py
clearml_agent/_vendor/chardet/johabfreq.py
clearml_agent-2.0.5.dist-info/LICENSE
clearml_agent-2.0.5.dist-info/METADATA
clearml_agent-2.0.5.dist-info/WHEEL
clearml_agent-2.0.5.dist-info/entry_points.txt
clearml_agent-2.0.5.dist-info/top_level.txt
clearml_agent-2.0.5.dist-info/RECORD
