Metadata-Version: 2.1
Name: clearml-agent
Version: 2.0.5
Summary: ClearML Agent - Auto-Magical DevOps for Deep Learning
Home-page: https://github.com/clearml/clearml-agent
Author: clearml
Author-email: clearml@clearml.ai
License: Apache License 2.0
Keywords: clearml trains devops machine deep learning agent automation hpc cluster
Platform: UNKNOWN
Classifier: Development Status :: 5 - Production/Stable
Classifier: Intended Audience :: Developers
Classifier: Intended Audience :: System Administrators
Classifier: Intended Audience :: Science/Research
Classifier: Operating System :: POSIX :: Linux
Classifier: Operating System :: MacOS :: MacOS X
Classifier: Operating System :: Microsoft
Classifier: Topic :: Scientific/Engineering :: Artificial Intelligence
Classifier: Topic :: Scientific/Engineering :: Image Recognition
Classifier: Topic :: System :: Logging
Classifier: Topic :: System :: Monitoring
Classifier: Programming Language :: Python :: 3.6
Classifier: Programming Language :: Python :: 3.7
Classifier: Programming Language :: Python :: 3.8
Classifier: Programming Language :: Python :: 3.9
Classifier: Programming Language :: Python :: 3.10
Classifier: Programming Language :: Python :: 3.11
Classifier: Programming Language :: Python :: 3.12
Classifier: Programming Language :: Python :: 3.13
Classifier: License :: OSI Approved :: Apache Software License
Requires-Dist: psutil (<7.1,>=3.4.2)
Requires-Dist: urllib3 (<3,>=1.21.1)
Requires-Dist: virtualenv (<21,>=16)
Requires-Dist: requests (<2.33,>=2.20.0)
Requires-Dist: setuptools ; python_version > "3.11"
Requires-Dist: pywin32 ; sys_platform == "win32"
